<?xml version ="1.0"?>
<LocalCache DownloadCode='90000416-6000-11D3-8CFE-0150048383C9'>
	<Bootstrap Version='11.0.5525.0' Size='89136'>OSE.EXE</Bootstrap>
	<Product Id='90170416-6000-11D3-8CFE-0150048383C9' Version='11.0.5614.0' ProductName='Microsoft Office FrontPage 2003' ProductNameQualified='FrontPage 2003'>FP11.MSI</Product>
	<File Id='CC561401.CAB' Size='1681457' MD5='1453BE63694162735E93A3E4C6586645' CacheLevel='2' RelativeSourcePath='CC561401.CAB' RelativeCachePath='CC561401.CAB'>CC561401.CAB</File>
	<File Id='CD561401.CAB' Size='323898' MD5='BA6D21B2FDCC070615BA822A94E64688' CacheLevel='2' RelativeSourcePath='CD561401.CAB' RelativeCachePath='CD561401.CAB'>CD561401.CAB</File>
	<File Id='CF561401.CAB' Size='2071027' MD5='9DBFCEE55AF8771EBA5D0C116F554110' CacheLevel='2' RelativeSourcePath='CF561401.CAB' RelativeCachePath='CF561401.CAB'>CF561401.CAB</File>
	<File Id='CL561401.CAB' Size='706243' MD5='3408A059E83994182473CB9B3BDD863A' CacheLevel='2' RelativeSourcePath='CL561401.CAB' RelativeCachePath='CL561401.CAB'>CL561401.CAB</File>
	<File Id='CM561401.CAB' Size='1232028' MD5='50D723084EA31EB396EE7C950C12C156' CacheLevel='2' RelativeSourcePath='CM561401.CAB' RelativeCachePath='CM561401.CAB'>CM561401.CAB</File>
	<File Id='CP561401.CAB' Size='2487448' MD5='F8B789C6EDD06A39D14BBC77AA3E7093' CacheLevel='2' RelativeSourcePath='CP561401.CAB' RelativeCachePath='CP561401.CAB'>CP561401.CAB</File>
	<File Id='CR561401.CAB' Size='2306744' MD5='56CFF3F0300AFE2DB5E6C2AF75E471D9' CacheLevel='2' RelativeSourcePath='CR561401.CAB' RelativeCachePath='CR561401.CAB'>CR561401.CAB</File>
	<File Id='CS561401.CAB' Size='611657' MD5='DFA30BC5A6E281CCF69B549F80B468B2' CacheLevel='2' RelativeSourcePath='CS561401.CAB' RelativeCachePath='CS561401.CAB'>CS561401.CAB</File>
	<File Id='DW20.ADM_1046' Size='37516' MD5='4D50BFBAACB867C824A33AEA93205B1B' CacheLevel='1' RelativeSourcePath='FILES\WINDOWS\INF\AER_1046.ADM' RelativeCachePath='FILES\WINDOWS\INF\AER_1046.ADM'>FILES\WINDOWS\INF\AER_1046.ADM</File>
	<File Id='DW20.EXE_0001' Size='620088' MD5='9FD3AAFF540394BDD9D196010B3F26AE' CacheLevel='1' RelativeSourcePath='FILES\PFILES\COMMON\MSSHARED\DW\DW20.EXE' RelativeCachePath='FILES\PFILES\COMMON\MSSHARED\DW\DW20.EXE'>FILES\PFILES\COMMON\MSSHARED\DW\DW20.EXE</File>
	<File Id='DWDCW20.DLL' Size='39992' MD5='5D537EFCFFB6848D9765D824FE266755' CacheLevel='1' RelativeSourcePath='FILES\PFILES\COMMON\MSSHARED\DW\DWDCW20.DLL' RelativeCachePath='FILES\PFILES\COMMON\MSSHARED\DW\DWDCW20.DLL'>FILES\PFILES\COMMON\MSSHARED\DW\DWDCW20.DLL</File>
	<File Id='DWINTL20.DLL_0001_1046' Size='110680' MD5='F78D9FD05E5500E1322B9D797DFE94A5' CacheLevel='1' RelativeSourcePath='FILES\PFILES\COMMON\MSSHARED\DW\1046\DWINTL20.DLL' RelativeCachePath='FILES\PFILES\COMMON\MSSHARED\DW\1046\DWINTL20.DLL'>FILES\PFILES\COMMON\MSSHARED\DW\1046\DWINTL20.DLL</File>
	<File Id='DWTRIG20.EXE' Size='34880' MD5='193D159EA2E807C67B718FDEFCAED47B' CacheLevel='1' RelativeSourcePath='FILES\PFILES\COMMON\MSSHARED\DW\DWTRIG20.EXE' RelativeCachePath='FILES\PFILES\COMMON\MSSHARED\DW\DWTRIG20.EXE'>FILES\PFILES\COMMON\MSSHARED\DW\DWTRIG20.EXE</File>
	<File Id='F2561421.CAB' Size='17304221' MD5='9C25E9298BBBA177C8FC9785C9B4BFE5' CacheLevel='2' RelativeSourcePath='F2561421.CAB' RelativeCachePath='F2561421.CAB'>F2561421.CAB</File>
	<File Id='F3561405.CAB' Size='1820326' MD5='42B90DB4F8A769EAEC149B5DAA4B59A2' CacheLevel='2' RelativeSourcePath='F3561405.CAB' RelativeCachePath='F3561405.CAB'>F3561405.CAB</File>
	<File Id='F4561401.CAB' Size='1280153' MD5='30A48FB353075F629101FD3992774C2C' CacheLevel='2' RelativeSourcePath='F4561401.CAB' RelativeCachePath='F4561401.CAB'>F4561401.CAB</File>
	<File Id='FP11.INI' Size='2957' MD5='098E29F8750B4CE653DFED8E62910791' CacheLevel='3' RelativeSourcePath='FILES\SETUP\INSTALAR.INI' RelativeCachePath='FILES\SETUP\INSTALAR.INI'>FILES\SETUP\INSTALAR.INI</File>
	<File Id='FP11.MSI' Size='2907136' MD5='A97EC6867FCE5C1DA9240B2638CE94D2' CacheLevel='1' RelativeSourcePath='FP11.MSI' RelativeCachePath='FP11.MSI'>FP11.MSI</File>
	<File Id='FV561405.CAB' Size='1862842' MD5='E4A164D985431B60A18D28EAB9F288A0' CacheLevel='2' RelativeSourcePath='FV561405.CAB' RelativeCachePath='FV561405.CAB'>FV561405.CAB</File>
	<File Id='IJ561401.CAB' Size='107046' MD5='E735D52807C4BFC7E1137DE151049B2E' CacheLevel='2' RelativeSourcePath='IJ561401.CAB' RelativeCachePath='IJ561401.CAB'>IJ561401.CAB</File>
	<File Id='IS561401.CAB' Size='38260' MD5='68AFB653DF592472B906256F979D30F5' CacheLevel='2' RelativeSourcePath='IS561401.CAB' RelativeCachePath='IS561401.CAB'>IS561401.CAB</File>
	<File Id='IU561401.CAB' Size='13650283' MD5='7FE9C34997267024FA6936BCE4BB583E' CacheLevel='2' RelativeSourcePath='IU561401.CAB' RelativeCachePath='IU561401.CAB'>IU561401.CAB</File>
	<File Id='M2561411.CAB' Size='51088' MD5='8B39C349787F901D0C39B6BAA4D99CB9' CacheLevel='2' RelativeSourcePath='M2561411.CAB' RelativeCachePath='M2561411.CAB'>M2561411.CAB</File>
	<File Id='M3561470.CAB' Size='5107769' MD5='61DC625745B01245661B2FCF94B36899' CacheLevel='2' RelativeSourcePath='M3561470.CAB' RelativeCachePath='M3561470.CAB'>M3561470.CAB</File>
	<File Id='M4561464.CAB' Size='12452640' MD5='2D4496142D364AB00C05EE3BB01CA916' CacheLevel='2' RelativeSourcePath='M4561464.CAB' RelativeCachePath='M4561464.CAB'>M4561464.CAB</File>
	<File Id='M9561401.CAB' Size='2301053' MD5='6C8101E67AA3A89EDE8C06DFC2C23456' CacheLevel='2' RelativeSourcePath='M9561401.CAB' RelativeCachePath='M9561401.CAB'>M9561401.CAB</File>
	<File Id='MC561412.CAB' Size='2277560' MD5='CBA159769FEE4B5DDA992DE3FE7F8D1E' CacheLevel='2' RelativeSourcePath='MC561412.CAB' RelativeCachePath='MC561412.CAB'>MC561412.CAB</File>
	<File Id='MG561411.CAB' Size='915510' MD5='59C8CCB35F260250DD5E34C1048E62AC' CacheLevel='2' RelativeSourcePath='MG561411.CAB' RelativeCachePath='MG561411.CAB'>MG561411.CAB</File>
	<File Id='MH561401.CAB' Size='2374394' MD5='115CD75BFF19872FDB125B01263E0D1C' CacheLevel='2' RelativeSourcePath='MH561401.CAB' RelativeCachePath='MH561401.CAB'>MH561401.CAB</File>
	<File Id='MT561411.CAB' Size='2532359' MD5='F3374DCEB727B22D3F19688BAA10B4F0' CacheLevel='2' RelativeSourcePath='MT561411.CAB' RelativeCachePath='MT561411.CAB'>MT561411.CAB</File>
	<File Id='O0561401.CAB' Size='30137' MD5='CEC7A713BBBD7CB9D559AAD4404967E8' CacheLevel='2' RelativeSourcePath='O0561401.CAB' RelativeCachePath='O0561401.CAB'>O0561401.CAB</File>
	<File Id='O1561489.CAB' Size='12497279' MD5='D374373146EA471F0BC88A620C855718' CacheLevel='2' RelativeSourcePath='O1561489.CAB' RelativeCachePath='O1561489.CAB'>O1561489.CAB</File>
	<File Id='O9561415.CAB' Size='193040' MD5='851689EC3B8D3B8E30603F6DDC9E6E36' CacheLevel='2' RelativeSourcePath='O9561415.CAB' RelativeCachePath='O9561415.CAB'>O9561415.CAB</File>
	<File Id='OCLEAN.DLL_1046' Size='224344' MD5='9D249CB781430514AB747CB83C167900' CacheLevel='1' RelativeSourcePath='FILES\PFILES\MSOFFICE\OFFICE11\OCLEAN.DLL' RelativeCachePath='FILES\PFILES\MSOFFICE\OFFICE11\OCLEAN.DLL'>FILES\PFILES\MSOFFICE\OFFICE11\OCLEAN.DLL</File>
	<File Id='OCLNCORE.OPC_1046' Size='494120' MD5='014C89C4867D77691BA928EBB1C43897' CacheLevel='1' RelativeSourcePath='FILES\PFILES\MSOFFICE\OFFICE11\OCLNCORE.OPC' RelativeCachePath='FILES\PFILES\MSOFFICE\OFFICE11\OCLNCORE.OPC'>FILES\PFILES\MSOFFICE\OFFICE11\OCLNCORE.OPC</File>
	<File Id='OCLNCUST.OPC_1046' Size='13275' MD5='14712AB9341AAA5BA811029F6498EE78' CacheLevel='1' RelativeSourcePath='FILES\PFILES\MSOFFICE\OFFICE11\OCLNCUST.OPC' RelativeCachePath='FILES\PFILES\MSOFFICE\OFFICE11\OCLNCUST.OPC'>FILES\PFILES\MSOFFICE\OFFICE11\OCLNCUST.OPC</File>
	<File Id='OCLNINTL.OPC_1046' Size='110050' MD5='5AE45C4F0EC49528EBCFE5F772DC5063' CacheLevel='1' RelativeSourcePath='FILES\PFILES\MSOFFICE\OFFICE11\1046\OCLNINTL.OPC' RelativeCachePath='FILES\PFILES\MSOFFICE\OFFICE11\1046\OCLNINTL.OPC'>FILES\PFILES\MSOFFICE\OFFICE11\1046\OCLNINTL.OPC</File>
	<File Id='OFFCLN.EXE_1046' Size='58456' MD5='955B0AAD009F450208F1C8E4BF491D6E' CacheLevel='1' RelativeSourcePath='FILES\PFILES\MSOFFICE\OFFICE11\OFFCLN.EXE' RelativeCachePath='FILES\PFILES\MSOFFICE\OFFICE11\OFFCLN.EXE'>FILES\PFILES\MSOFFICE\OFFICE11\OFFCLN.EXE</File>
	<File Id='OSE.EXE' Size='89136' MD5='7A56CF3E3F12E8AF599963B16F50FB6A' CacheLevel='1' RelativeSourcePath='FILES\SETUP\OSE.EXE' RelativeCachePath='FILES\SETUP\OSE.EXE'>FILES\SETUP\OSE.EXE</File>
	<File Id='PA561401.CAB' Size='1740699' MD5='A7266A2ED40CE54E8FD20F79E29F50E7' CacheLevel='2' RelativeSourcePath='PA561401.CAB' RelativeCachePath='PA561401.CAB'>PA561401.CAB</File>
	<File Id='PR103369.CAB' Size='5755051' MD5='8050072FBF7D6A4B666AC10F7CAC661E' CacheLevel='2' RelativeSourcePath='PR103369.CAB' RelativeCachePath='PR103369.CAB'>PR103369.CAB</File>
	<File Id='PR104602.CAB' Size='4608918' MD5='B929A44D485F5EDD5EC41735C601DAC4' CacheLevel='2' RelativeSourcePath='PR104602.CAB' RelativeCachePath='PR104602.CAB'>PR104602.CAB</File>
	<File Id='PR308204.CAB' Size='7706491' MD5='54BC2E21F2B4490882F3DC61F8C36EC6' CacheLevel='2' RelativeSourcePath='PR308204.CAB' RelativeCachePath='PR308204.CAB'>PR308204.CAB</File>
	<File Id='PSS10O.CHM_1046' Size='11060' MD5='FD076A1F16D098547965968FE03AB3FC' CacheLevel='1' RelativeSourcePath='FILES\PFILES\MSOFFICE\OFFICE11\1046\PSS10O.CHM' RelativeCachePath='FILES\PFILES\MSOFFICE\OFFICE11\1046\PSS10O.CHM'>FILES\PFILES\MSOFFICE\OFFICE11\1046\PSS10O.CHM</File>
	<File Id='PSS10R.CHM_1046' Size='11290' MD5='55BC22640030833523B89694DA19980F' CacheLevel='1' RelativeSourcePath='FILES\PFILES\MSOFFICE\OFFICE11\1046\PSS10R.CHM' RelativeCachePath='FILES\PFILES\MSOFFICE\OFFICE11\1046\PSS10R.CHM'>FILES\PFILES\MSOFFICE\OFFICE11\1046\PSS10R.CHM</File>
	<File Id='SETUP.CHM_1046' Size='279729' MD5='4C30A472149621A96C937BC6B695A4B3' CacheLevel='1' RelativeSourcePath='FILES\PFILES\MSOFFICE\OFFICE11\1046\SETUP.CHM' RelativeCachePath='FILES\PFILES\MSOFFICE\OFFICE11\1046\SETUP.CHM'>FILES\PFILES\MSOFFICE\OFFICE11\1046\SETUP.CHM</File>
	<File Id='SETUP.EXE_1046' Size='417880' MD5='41B7DAD0C38375B118674BD619A395EB' CacheLevel='3' RelativeSourcePath='INSTALAR.EXE' RelativeCachePath='INSTALAR.EXE'>INSTALAR.EXE</File>
	<File Id='SKU017.CAB' Size='8143' MD5='D0FA451305C380B40EBC56F641E37177' CacheLevel='2' RelativeSourcePath='SKU017.CAB' RelativeCachePath='SKU017.CAB'>SKU017.CAB</File>
	<File Id='SKU017.XML_0002_1046' Size='417373' MD5='D9187591B69B57759FD4E283B7F1274C' CacheLevel='1' RelativeSourcePath='SKU017.XML' RelativeCachePath='SKU017.XML'>SKU017.XML</File>
	<File Id='TR308222.CAB' Size='2056750' MD5='3E4816C7E94B935DFA5A51408BC87B7D' CacheLevel='2' RelativeSourcePath='TR308222.CAB' RelativeCachePath='TR308222.CAB'>TR308222.CAB</File>
	<File Id='V3561410.CAB' Size='2060636' MD5='3CB8990FABD0DF6EEE40EABF0F2547C7' CacheLevel='2' RelativeSourcePath='V3561410.CAB' RelativeCachePath='V3561410.CAB'>V3561410.CAB</File>
	<File Id='YA561410.CAB' Size='8350463' MD5='8298B1A0F9E271B94B231F6303798A11' CacheLevel='2' RelativeSourcePath='YA561410.CAB' RelativeCachePath='YA561410.CAB'>YA561410.CAB</File>
	<File Id='YB561434.CAB' Size='8319147' MD5='DFDC3BF66731517275215F0BE39A4F06' CacheLevel='2' RelativeSourcePath='YB561434.CAB' RelativeCachePath='YB561434.CAB'>YB561434.CAB</File>
	<File Id='YC561409.CAB' Size='627341' MD5='F15939AB9E0FFB18CFEDD9548D947C6B' CacheLevel='2' RelativeSourcePath='YC561409.CAB' RelativeCachePath='YC561409.CAB'>YC561409.CAB</File>
	<File Id='YH561411.CAB' Size='4586946' MD5='41077C83F2F38972BC4FFA56ABC66150' CacheLevel='2' RelativeSourcePath='YH561411.CAB' RelativeCachePath='YH561411.CAB'>YH561411.CAB</File>
	<File Id='YI561401.CAB' Size='1440029' MD5='3876C08E3F0293C2E3269642E07C76CA' CacheLevel='2' RelativeSourcePath='YI561401.CAB' RelativeCachePath='YI561401.CAB'>YI561401.CAB</File>
	<File Id='YM561403.CAB' Size='63208' MD5='7B49CC9DFF41085FBF2A8838E44B9BC2' CacheLevel='2' RelativeSourcePath='YM561403.CAB' RelativeCachePath='YM561403.CAB'>YM561403.CAB</File>
	<File Id='YO561409.CAB' Size='586621' MD5='1BCC28FE0B920AA3E13BCC06D7D8F99F' CacheLevel='2' RelativeSourcePath='YO561409.CAB' RelativeCachePath='YO561409.CAB'>YO561409.CAB</File>
	<File Id='YT561401.CAB' Size='14446' MD5='3ED4E10CEB2AFE145DF50BFE4B46FC3D' CacheLevel='2' RelativeSourcePath='YT561401.CAB' RelativeCachePath='YT561401.CAB'>YT561401.CAB</File>
	<File Id='ZC561406.CAB' Size='2679261' MD5='F966A669F2C2FE695C28DA5A1559EFDA' CacheLevel='2' RelativeSourcePath='ZC561406.CAB' RelativeCachePath='ZC561406.CAB'>ZC561406.CAB</File>
	<File Id='ZD561404.CAB' Size='1732854' MD5='B79B4A3BA928E0B4983D5E90D09D884B' CacheLevel='2' RelativeSourcePath='ZD561404.CAB' RelativeCachePath='ZD561404.CAB'>ZD561404.CAB</File>
	<File Id='ZE561409.CAB' Size='764432' MD5='78E8FE97B1EFB3232D9D5E856FFCF7DA' CacheLevel='2' RelativeSourcePath='ZE561409.CAB' RelativeCachePath='ZE561409.CAB'>ZE561409.CAB</File>
	<File Id='ZF561402.CAB' Size='2248811' MD5='C42B842591C3AE0773B09ACDC62586FF' CacheLevel='2' RelativeSourcePath='ZF561402.CAB' RelativeCachePath='ZF561402.CAB'>ZF561402.CAB</File>
	<File Id='ZG561401.CAB' Size='47824' MD5='64672C186C7C25A456A0705E60269295' CacheLevel='2' RelativeSourcePath='ZG561401.CAB' RelativeCachePath='ZG561401.CAB'>ZG561401.CAB</File>
	<File Id='ZH561411.CAB' Size='243689' MD5='5EDBCC902ED2C48BFEFBCDEB1884FEC5' CacheLevel='2' RelativeSourcePath='ZH561411.CAB' RelativeCachePath='ZH561411.CAB'>ZH561411.CAB</File>
	<File Id='ZJ561401.CAB' Size='103723' MD5='856185E43CA39E878D41D0F8EF624513' CacheLevel='2' RelativeSourcePath='ZJ561401.CAB' RelativeCachePath='ZJ561401.CAB'>ZJ561401.CAB</File>
	<File Id='ZK561401.CAB' Size='147457' MD5='7B218D997512741CC9BA98DABE2A4DE5' CacheLevel='2' RelativeSourcePath='ZK561401.CAB' RelativeCachePath='ZK561401.CAB'>ZK561401.CAB</File>
	<File Id='ZM561401.CAB' Size='107454' MD5='5042DD050258E731AD2C679E3AEA9B7B' CacheLevel='2' RelativeSourcePath='ZM561401.CAB' RelativeCachePath='ZM561401.CAB'>ZM561401.CAB</File>
	<File Id='ZN561401.CAB' Size='274001' MD5='CD96364CC3356D5F7B9D9430E1FC3A1C' CacheLevel='2' RelativeSourcePath='ZN561401.CAB' RelativeCachePath='ZN561401.CAB'>ZN561401.CAB</File>
	<File Id='ZQ561401.CAB' Size='668276' MD5='3BB024EEBE770DE12EE6C9808295AF91' CacheLevel='2' RelativeSourcePath='ZQ561401.CAB' RelativeCachePath='ZQ561401.CAB'>ZQ561401.CAB</File>
	<File Id='ZR561409.CAB' Size='23383' MD5='7C2ABEC7E1FE09112B3CA147EE34C909' CacheLevel='2' RelativeSourcePath='ZR561409.CAB' RelativeCachePath='ZR561409.CAB'>ZR561409.CAB</File>
	<File Id='ZS561401.CAB' Size='441429' MD5='5CA61BA04791D81D94EEDEF7030E1D22' CacheLevel='2' RelativeSourcePath='ZS561401.CAB' RelativeCachePath='ZS561401.CAB'>ZS561401.CAB</File>
	<File Id='ZT561401.CAB' Size='353051' MD5='6E15A50A08C077AC8762AB67FFC6B945' CacheLevel='2' RelativeSourcePath='ZT561401.CAB' RelativeCachePath='ZT561401.CAB'>ZT561401.CAB</File>
	<File Id='ZV561401.CAB' Size='91858' MD5='EC7D4D9BAAFBC6DD4120EA435ACB9903' CacheLevel='2' RelativeSourcePath='ZV561401.CAB' RelativeCachePath='ZV561401.CAB'>ZV561401.CAB</File>
	<File Id='ZY561438.CAB' Size='464584' MD5='170FA8D5E5DE5E032AFAFF2565231215' CacheLevel='2' RelativeSourcePath='ZY561438.CAB' RelativeCachePath='ZY561438.CAB'>ZY561438.CAB</File>
	<File Id='ZZ561401.CAB' Size='6291' MD5='83CF896646DD6CCAA498BAA8C65A6160' CacheLevel='2' RelativeSourcePath='ZZ561401.CAB' RelativeCachePath='ZZ561401.CAB'>ZZ561401.CAB</File>
	<Source Id='90170416-6000-11D3-8CFE-0150048383C9'></Source>
</LocalCache>
